pyQuirk/__init__.py
pyQuirk/_version.py
pyQuirk/quirk.py
pyQuirk/labextension/package.json
pyQuirk/labextension/static/261.f77de6bad4735270a40d.js
pyQuirk/labextension/static/41a83a01f054021887ea5ae4d92c0465a42459f92b86faa902911f79f4cd1bb9.html
pyQuirk/labextension/static/486.3084da9b112e37a81524.js
pyQuirk/labextension/static/486.3084da9b112e37a81524.js.LICENSE.txt
pyQuirk/labextension/static/568.3dc27f56b4c1aa824d38.js
pyQuirk/labextension/static/remoteEntry.d79f14029fd9ef50cea2.js
pyQuirk/labextension/static/style.js
pyQuirk/labextension/static/third-party-licenses.json
pyQuirk/nbextension/extension.js
pyQuirk/nbextension/index.js
pyQuirk/nbextension/index.js.LICENSE.txt
pyQuirk-0.1.7b0.data/data/etc/jupyter/nbconfig/notebook.d/pyQuirk.json
pyQuirk-0.1.7b0.data/data/share/jupyter/labextensions/pyquirk/install.json
pyQuirk-0.1.7b0.data/data/share/jupyter/labextensions/pyquirk/package.json
pyQuirk-0.1.7b0.data/data/share/jupyter/labextensions/pyquirk/static/261.f77de6bad4735270a40d.js
pyQuirk-0.1.7b0.data/data/share/jupyter/labextensions/pyquirk/static/41a83a01f054021887ea5ae4d92c0465a42459f92b86faa902911f79f4cd1bb9.html
pyQuirk-0.1.7b0.data/data/share/jupyter/labextensions/pyquirk/static/486.3084da9b112e37a81524.js
pyQuirk-0.1.7b0.data/data/share/jupyter/labextensions/pyquirk/static/486.3084da9b112e37a81524.js.LICENSE.txt
pyQuirk-0.1.7b0.data/data/share/jupyter/labextensions/pyquirk/static/568.3dc27f56b4c1aa824d38.js
pyQuirk-0.1.7b0.data/data/share/jupyter/labextensions/pyquirk/static/remoteEntry.d79f14029fd9ef50cea2.js
pyQuirk-0.1.7b0.data/data/share/jupyter/labextensions/pyquirk/static/style.js
pyQuirk-0.1.7b0.data/data/share/jupyter/labextensions/pyquirk/static/third-party-licenses.json
pyQuirk-0.1.7b0.data/data/share/jupyter/nbextensions/pyquirk/extension.js
pyQuirk-0.1.7b0.data/data/share/jupyter/nbextensions/pyquirk/index.js
pyQuirk-0.1.7b0.data/data/share/jupyter/nbextensions/pyquirk/index.js.LICENSE.txt
pyQuirk-0.1.7b0.dist-info/LICENSE
pyQuirk-0.1.7b0.dist-info/METADATA
pyQuirk-0.1.7b0.dist-info/WHEEL
pyQuirk-0.1.7b0.dist-info/top_level.txt
pyQuirk-0.1.7b0.dist-info/RECORD
